LICENSE.txt
MANIFEST.in
README.md
diagram.png
genome_map.png
setup.cfg
setup.py
COGor/__init__.py
COGor/cogor.py
COGor/consensus.py
COGor/program_processor.py
COGor/track_manager.py
COGor.egg-info/PKG-INFO
COGor.egg-info/SOURCES.txt
COGor.egg-info/dependency_links.txt
COGor.egg-info/requires.txt
COGor.egg-info/top_level.txt
COGor/COGor-data/legend_text.csv
COGor/__pycache__/__init__.cpython-310.pyc
COGor/__pycache__/consensus.cpython-310.pyc
COGor/__pycache__/program_processor.cpython-310.pyc
COGor/__pycache__/track_manager.cpython-310.pyc